clickmouse/__init__.py
clickmouse/__main__.py
clickmouse/command_tools.py
clickmouse/version.py
clickmouse-2.1.1.dist-info/licenses/LICENSE
clickmouse-2.1.1.dist-info/METADATA
clickmouse-2.1.1.dist-info/WHEEL
clickmouse-2.1.1.dist-info/entry_points.txt
clickmouse-2.1.1.dist-info/top_level.txt
clickmouse-2.1.1.dist-info/RECORD
