Metadata-Version: 2.4
Name: ClickMouse
Version: 2.1.1
Summary: 基于Python的鼠标连点工具
Home-page: https://github.com/xystudio/pyClickMouse
Author: xystudio
Author-email: xystudio <173288240@qq.com>
Project-URL: homepage, https://github.com/xystudio/pyClickMouse
Keywords: mouse,click,automation,clickmouse
Classifier: Programming Language :: Python :: 3
Classifier: License :: OSI Approved :: MIT License
Classifier: Operating System :: OS Independent
Requires-Python: >=3.8
License-File: LICENSE
Requires-Dist: pyautogui
Dynamic: author
Dynamic: home-page
Dynamic: license-file
Dynamic: requires-python
